json_insert/__init__.py
json_insert/streamer.py
tests/__init__.py
tests/test_streamer.py
json_insert-0.1.0.dist-info/LICENSE
json_insert-0.1.0.dist-info/METADATA
json_insert-0.1.0.dist-info/WHEEL
json_insert-0.1.0.dist-info/top_level.txt
json_insert-0.1.0.dist-info/RECORD
